{
  "version": "2.4.1",
  "summary": {
    "title": "Threat Dragon _ UAH",
    "owner": "Koldo",
    "description": "",
    "id": 0
  },
  "detail": {
    "contributors": [],
    "diagrams": [
      {
        "id": 0,
        "title": "Client 1",
        "diagramType": "STRIDE",
        "placeholder": "Descripción de nuevo diagrama STRIDE",
        "thumbnail": "./public/content/images/thumbnail.stride.jpg",
        "version": "2.4.1",
        "cells": []
      },
      {
        "id": 1,
        "title": "Client 2",
        "diagramType": "STRIDE",
        "placeholder": "Descripción de nuevo diagrama STRIDE",
        "thumbnail": "./public/content/images/thumbnail.stride.jpg",
        "version": "2.4.1",
        "cells": []
      },
      {
        "id": 2,
        "title": "Client 3",
        "diagramType": "STRIDE",
        "placeholder": "Descripción de nuevo diagrama STRIDE",
        "thumbnail": "./public/content/images/thumbnail.stride.jpg",
        "version": "2.4.1",
        "cells": []
      },
      {
        "id": 3,
        "title": "Client3_PC",
        "diagramType": "STRIDE",
        "placeholder": "Descripción de nuevo diagrama STRIDE",
        "thumbnail": "./public/content/images/thumbnail.stride.jpg",
        "version": "2.4.1",
        "cells": []
      },
      {
        "id": 4,
        "title": "Google Cloud Server",
        "diagramType": "STRIDE",
        "placeholder": "Descripción de nuevo diagrama STRIDE",
        "thumbnail": "./public/content/images/thumbnail.stride.jpg",
        "version": "2.4.1",
        "cells": []
      },
      {
        "id": 5,
        "title": "Google Cloud Server",
        "diagramType": "STRIDE",
        "placeholder": "Descripción de nuevo diagrama STRIDE",
        "thumbnail": "./public/content/images/thumbnail.stride.jpg",
        "version": "2.4.1",
        "cells": []
      }
    ],
    "diagramTop": 6,
    "reviewer": "",
    "threatTop": 0
  }
}